markdpy/__init__.py
markdpy/cli/__init__.py
markdpy/cli/main.py
markdpy/config/__init__.py
markdpy/config/models.py
markdpy/config/settings.py
markdpy/exporter/__init__.py
markdpy/exporter/generator.py
markdpy/renderer/__init__.py
markdpy/renderer/engine.py
markdpy/renderer/link_processor.py
markdpy/security/__init__.py
markdpy/security/path_validator.py
markdpy/server/__init__.py
markdpy/server/app.py
markdpy/server/banner.py
markdpy/server/dependencies.py
markdpy/server/middleware.py
markdpy/server/websocket.py
markdpy/server/routers/__init__.py
markdpy/server/routers/v1/__init__.py
markdpy/server/routers/v1/api.py
markdpy/server/routers/v1/ui.py
markdpy/server/routers/v1/ws.py
markdpy/server/utils/__init__.py
markdpy/server/utils/handlers.py
markdpy/server/utils/setup.py
markdpy/static/css/main.css
markdpy/static/css/syntax-dark.css
markdpy/static/css/syntax-light.css
markdpy/static/css/themes/dark.css
markdpy/static/css/themes/light.css
markdpy/static/css/themes/pygments-monokai.css
markdpy/static/images/terminal.png
markdpy/static/js/mermaid.js
markdpy/static/js/reload.js
markdpy/static/js/theme.js
markdpy/telemetry/__init__.py
markdpy/telemetry/telemetry.py
markdpy/templates/base.html
markdpy/templates/directory.html
markdpy/templates/error.html
markdpy/templates/single.html
markdpy/watcher/__init__.py
markdpy/watcher/observer.py
markdpy-0.1.3.dist-info/METADATA
markdpy-0.1.3.dist-info/WHEEL
markdpy-0.1.3.dist-info/entry_points.txt
markdpy-0.1.3.dist-info/licenses/LICENSE
markdpy-0.1.3.dist-info/RECORD
