Metadata-Version: 2.4
Name: markdpy
Version: 0.1.3
Summary: Python-based markdown preview server with live reload, themes, and static export
Project-URL: Homepage, https://github.com/eosho/markdpy
Project-URL: Documentation, https://github.com/eosho/markdpy#readme
Project-URL: Repository, https://github.com/eosho/markdpy
Project-URL: Issues, https://github.com/eosho/markdpy/issues
Author: markdpy contributors
License: MIT
License-File: LICENSE
Keywords: documentation,live-reload,markdown,preview,server
Classifier: Development Status :: 3 - Alpha
Classifier: Intended Audience :: Developers
Classifier: License :: OSI Approved :: MIT License
Classifier: Programming Language :: Python :: 3
Classifier: Programming Language :: Python :: 3.10
Classifier: Programming Language :: Python :: 3.11
Classifier: Programming Language :: Python :: 3.12
Classifier: Topic :: Documentation
Classifier: Topic :: Software Development :: Documentation
Requires-Python: >=3.10
Requires-Dist: aiofiles>=24.1.0
Requires-Dist: fastapi>=0.118.0
Requires-Dist: jinja2>=3.1.6
Requires-Dist: markdown>=3.9.0
Requires-Dist: pygments>=2.19.2
Requires-Dist: pymdown-extensions>=10.3.0
Requires-Dist: typer>=0.19.2
Requires-Dist: uvicorn[standard]>=0.37.0
Requires-Dist: watchdog>=6.0.0
Provides-Extra: dev
Requires-Dist: black>=25.9.0; extra == 'dev'
Requires-Dist: httpx>=0.28.0; extra == 'dev'
Requires-Dist: mypy>=1.18.2; extra == 'dev'
Requires-Dist: pre-commit>=4.2.0; extra == 'dev'
Requires-Dist: pyright>=1.1.399; extra == 'dev'
Requires-Dist: pytest-asyncio>=0.26.0; extra == 'dev'
Requires-Dist: pytest-cov>=7.0.0; extra == 'dev'
Requires-Dist: pytest-xdist>=3.8.0; extra == 'dev'
Requires-Dist: pytest>=8.3.5; extra == 'dev'
Requires-Dist: ruff>=0.11.6; extra == 'dev'
